{
  "directed": true,
  "first_noted_at": "2026-02-28",
  "from": "org/un/org@university-of-waterloo",
  "id": "citation-org-university-of-waterloo-uw-svf-fall-2019",
  "last_verified_at": "2026-02-28",
  "notes": "Derived citation edge from footnote [^uw-svf-fall-2019] in org/un/org@university-of-waterloo",
  "relation": "cites",
  "sources": [
    "source/uw/source@uw-svf-fall-2019"
  ],
  "strength": null,
  "to": "source/uw/source@uw-svf-fall-2019",
  "valid_from": null,
  "valid_to": null
}
